flylog/__init__.py
flylog/constants.py
flylog/api/__init__.py
flylog/api/client.py
flylog/api/log_handler.py
flylog/server/__init__.py
flylog/server/log.py
flylog/server/server.py
flylog/server/six.py
flylog/server/utils.py
flylog/server/backends/__init__.py
flylog/server/backends/ding.py
flylog/server/backends/mail.py
flylog/server/backends/sendcloud.py
flylog-0.2.6.data/scripts/run_flylog.py
flylog-0.2.6.dist-info/METADATA
flylog-0.2.6.dist-info/WHEEL
flylog-0.2.6.dist-info/top_level.txt
flylog-0.2.6.dist-info/RECORD
