Metadata-Version: 2.1
Name: flylog
Version: 0.2.6
Summary: make log fly to mail or other
Home-page: https://github.com/dantezhu/flylog
Author: dantezhu
Author-email: dantezhu <zny2008@gmail.com>
License: BSD
Project-URL: Homepage, https://github.com/dantezhu/flylog
Platform: any
Requires-Dist: requests
